langmem_adapter/__init__.py
langmem_adapter/openai_agents_sdk.py
langmem_adapter-0.1.0.dist-info/METADATA
langmem_adapter-0.1.0.dist-info/WHEEL
langmem_adapter-0.1.0.dist-info/entry_points.txt
langmem_adapter-0.1.0.dist-info/RECORD
