Metadata-Version: 2.4
Name: langmem-adapter
Version: 0.1.0
Summary: Add your description here
Author-email: Muhammad Junaid <mr.junaidshaukat@gmail.com>
Requires-Python: >=3.13
Requires-Dist: openai-agents>=0.0.7
